pyutils/__init__.py
pyutils/base_sqlite_db.py
pyutils/my_log.py
pyutils/utils.py
pyutils/zip.py
pripy_utils-0.1.2.dist-info/METADATA
pripy_utils-0.1.2.dist-info/WHEEL
pripy_utils-0.1.2.dist-info/top_level.txt
pripy_utils-0.1.2.dist-info/RECORD
