Metadata-Version: 2.4
Name: pripy-utils
Version: 0.1.2
Summary: 个人python工具集
Author-email: JAYSENLIN <jaysen.lin@foxmail.com>
License-Expression: MIT AND (Apache-2.0 OR BSD-2-Clause)
Project-URL: Homepage, https://home.codelin.vip
Project-URL: Documentation, https://deepseeksblog.web.app/
Project-URL: Repository, https://github.com/linjonh/pripy-utils
Project-URL: Official Website, https://codelin.vip
Keywords: utils,mylog,zip,sqlite3,database
Requires-Python: >=2.7
Requires-Dist: requests>=2.31.0
